odoo/addons/product_brand/README.rst
odoo/addons/product_brand/__init__.py
odoo/addons/product_brand/__manifest__.py
odoo/addons/product_brand/i18n/ca.po
odoo/addons/product_brand/i18n/de.po
odoo/addons/product_brand/i18n/es.po
odoo/addons/product_brand/i18n/es_AR.po
odoo/addons/product_brand/i18n/fr.po
odoo/addons/product_brand/i18n/fr_FR.po
odoo/addons/product_brand/i18n/hr.po
odoo/addons/product_brand/i18n/it.po
odoo/addons/product_brand/i18n/nb_NO.po
odoo/addons/product_brand/i18n/nl.po
odoo/addons/product_brand/i18n/nl_NL.po
odoo/addons/product_brand/i18n/pl.po
odoo/addons/product_brand/i18n/product_brand.pot
odoo/addons/product_brand/i18n/pt.po
odoo/addons/product_brand/i18n/pt_BR.po
odoo/addons/product_brand/i18n/sl.po
odoo/addons/product_brand/models/__init__.py
odoo/addons/product_brand/models/product_brand.py
odoo/addons/product_brand/models/product_template.py
odoo/addons/product_brand/readme/CONTRIBUTORS.md
odoo/addons/product_brand/readme/CREDITS.md
odoo/addons/product_brand/readme/DESCRIPTION.md
odoo/addons/product_brand/readme/ROADMAP.md
odoo/addons/product_brand/readme/USAGE.md
odoo/addons/product_brand/reports/__init__.py
odoo/addons/product_brand/reports/account_invoice_report.py
odoo/addons/product_brand/reports/account_invoice_report_view.xml
odoo/addons/product_brand/reports/sale_report.py
odoo/addons/product_brand/reports/sale_report_view.xml
odoo/addons/product_brand/security/ir.model.access.csv
odoo/addons/product_brand/static/description/icon.png
odoo/addons/product_brand/static/description/index.html
odoo/addons/product_brand/tests/__init__.py
odoo/addons/product_brand/tests/common.py
odoo/addons/product_brand/tests/test_product_brand.py
odoo/addons/product_brand/views/product_brand_view.xml
odoo_addon_product_brand-19.0.1.0.0.2.dist-info/METADATA
odoo_addon_product_brand-19.0.1.0.0.2.dist-info/WHEEL
odoo_addon_product_brand-19.0.1.0.0.2.dist-info/top_level.txt
odoo_addon_product_brand-19.0.1.0.0.2.dist-info/RECORD
