Metadata-Version: 2.1
Name: odoo-addon-product_brand
Version: 19.0.1.0.0.2
Requires-Dist: odoo==19.0.*
Summary: Product Brand Manager
Home-page: https://github.com/OCA/brand
License: AGPL-3
Author: NetAndCo, Akretion, Prisnet Telecommunications SA, MONK Software, SerpentCS Pvt. Ltd., Tecnativa, Kaushal Prajapati, Odoo Community Association (OCA)
Author-email: support@odoo-community.org
Classifier: Programming Language :: Python
Classifier: Framework :: Odoo
Classifier: Framework :: Odoo :: 19.0
Classifier: License :: OSI Approved :: GNU Affero General Public License v3
Classifier: Development Status :: 6 - Mature
